{"inkVersion":21,"root":[["\n",{"->":"main"},["done",{"#f":5,"#n":"g-0"}],null],"done",{"main":["ev",{"VAR?":"catName"},"out","/ev","^ has so much dirt on her fur! ","#","^speaker:You","/#","\n","^I'll give her a bath to clean her up.","\n","^(Drag the soap to clean ","ev",{"VAR?":"catName"},"out","/ev","^)","\n","end",{"#f":1}],"catCleaned":["ev",{"VAR?":"catName"},"out","/ev","^ is purr-fectly clean now!  ","#","^speaker:You","/#","\n","^Look at that beautiful kitty :)","\n","ev",{"x()":"blackOut"},"pop","/ev","\n","end",{"#f":1}],"global decl":["ev","str","^Bloo","/str",{"VAR=":"catName"},"/ev","end",null],"#f":1}],"listDefs":{}}